CONTRIBUTING.md
LICENSE.md
MANIFEST.in
README.md
setup.py
django_muid/__init__.py
django_muid/fields.py
django_muid/muid.py
django_muid/validators.py
django_muid.egg-info/PKG-INFO
django_muid.egg-info/SOURCES.txt
django_muid.egg-info/dependency_links.txt
django_muid.egg-info/requires.txt
django_muid.egg-info/top_level.txt