Metadata-Version: 2.1
Name: django-muid
Version: 1.0.3
Summary: MUID field for Django
Home-page: https://github.com/angelcamelot/django-muid
Author: Angel Camelot
Author-email: dupeyron.camelot@gmail.com
Classifier: Development Status :: 3 - Alpha
Classifier: Intended Audience :: Developers
Classifier: License :: OSI Approved :: MIT License
Classifier: Operating System :: OS Independent
Classifier: Programming Language :: Python :: 3
Requires-Python: >=3.6
License-File: LICENSE.md
